odoo10_addon_website_sale_require_login-10.0.1.1.0-py2.7-nspkg.pth
odoo/addons/website_sale_require_login/README.rst
odoo/addons/website_sale_require_login/__init__.py
odoo/addons/website_sale_require_login/__manifest__.py
odoo/addons/website_sale_require_login/controllers/__init__.py
odoo/addons/website_sale_require_login/controllers/main.py
odoo/addons/website_sale_require_login/demo/demo_assets.xml
odoo/addons/website_sale_require_login/i18n/it.po
odoo/addons/website_sale_require_login/i18n/sl.po
odoo/addons/website_sale_require_login/static/description/icon.png
odoo/addons/website_sale_require_login/static/src/js/website_sale_tour_buy_login.tour.js
odoo/addons/website_sale_require_login/tests/__init__.py
odoo/addons/website_sale_require_login/tests/test_checkout.py
odoo/addons/website_sale_require_login/views/website_sale.xml
odoo10_addon_website_sale_require_login-10.0.1.1.0.dist-info/DESCRIPTION.rst
odoo10_addon_website_sale_require_login-10.0.1.1.0.dist-info/METADATA
odoo10_addon_website_sale_require_login-10.0.1.1.0.dist-info/RECORD
odoo10_addon_website_sale_require_login-10.0.1.1.0.dist-info/WHEEL
odoo10_addon_website_sale_require_login-10.0.1.1.0.dist-info/metadata.json
odoo10_addon_website_sale_require_login-10.0.1.1.0.dist-info/namespace_packages.txt
odoo10_addon_website_sale_require_login-10.0.1.1.0.dist-info/top_level.txt
