Metadata-Version: 2.0
Name: odoo10-addon-website-sale-require-login
Version: 10.0.1.1.0
Summary: Force users to login for buying
Home-page: http://www.antiun.com
Author: Tecnativa, LasLabs, Odoo Community Association (OCA)
Author-email: support@odoo-community.org
License: AGPL-3
Platform: UNKNOWN
Classifier: Programming Language :: Python
Classifier: Framework :: Odoo
Classifier: License :: OSI Approved :: GNU Affero General Public License v3
Requires-Python: ~=2.7
Requires-Dist: odoo (<10.1dev,>=10.0)
Requires-Dist: odoo10-addon-website-sale-suggest-create-account
